dialectic/__init__.py
dialectic/inference.py
dialectic/parse.py
dialectic/sentence.py
dialectic-0.3.2.dist-info/LICENSE
dialectic-0.3.2.dist-info/METADATA
dialectic-0.3.2.dist-info/WHEEL
dialectic-0.3.2.dist-info/top_level.txt
dialectic-0.3.2.dist-info/RECORD
