Metadata-Version: 2.1
Name: dialectic
Version: 0.3.2
Summary: Mathematical Logic
Home-page: https://github.com/virtualchamber/Tingle
Author: Ali Soltani Rad
Author-email: soltaniradali@gmail.com
License: UNKNOWN
Platform: UNKNOWN
Classifier: Programming Language :: Python :: 3
Classifier: License :: OSI Approved :: MIT License
Classifier: Operating System :: OS Independent
Requires-Python: >=3.7
